metasporecli/__init__.py
metasporecli/__main__.py
metasporecli/flow.py
metasporecli/main.py
metasporecli-0.1.3.dist-info/METADATA
metasporecli-0.1.3.dist-info/WHEEL
metasporecli-0.1.3.dist-info/entry_points.txt
metasporecli-0.1.3.dist-info/top_level.txt
metasporecli-0.1.3.dist-info/RECORD
