Metadata-Version: 2.1
Name: metasporecli
Version: 0.1.3
Summary: metasporecli: Command-line Interface for MetaSpore Flow Management
Author-email: DMetaSoul <opensource@dmetasoul.com>
License: Apache-2.0
Project-URL: Homepage, https://github.com/meta-soul/MetaSpore/tree/main/python/metasporecli
Project-URL: Bug Tracker, https://github.com/meta-soul/MetaSpore/issues
Classifier: Programming Language :: Python :: 3
Classifier: License :: OSI Approved :: Apache Software License
Classifier: Operating System :: OS Independent
Requires-Python: >=3.8
Requires-Dist: metasporeflow (~=0.1.3)
